nextcloud_async/__init__.py
nextcloud_async/exceptions.py
nextcloud_async/helpers.py
nextcloud_async/api/__init__.py
nextcloud_async/api/loginflow.py
nextcloud_async/api/maps.py
nextcloud_async/api/wipe.py
nextcloud_async/api/dav/__init__.py
nextcloud_async/api/dav/files.py
nextcloud_async/api/ocs/__init__.py
nextcloud_async/api/ocs/apps.py
nextcloud_async/api/ocs/groupfolders.py
nextcloud_async/api/ocs/groups.py
nextcloud_async/api/ocs/ldap.py
nextcloud_async/api/ocs/notifications.py
nextcloud_async/api/ocs/shares.py
nextcloud_async/api/ocs/status.py
nextcloud_async/api/ocs/users.py
nextcloud_async/api/ocs/talk/__init__.py
nextcloud_async/api/ocs/talk/constants.py
nextcloud_async/api/ocs/talk/exceptions.py
nextcloud_async/api/ocs/talk/rich_objects.py
nextcloud_async-0.0.10.dist-info/LICENSE
nextcloud_async-0.0.10.dist-info/METADATA
nextcloud_async-0.0.10.dist-info/WHEEL
nextcloud_async-0.0.10.dist-info/top_level.txt
nextcloud_async-0.0.10.dist-info/RECORD
