Metadata-Version: 2.2
Name: nextcloud_async
Version: 0.0.10
Summary: Asynchronous client library for Nextcloud
Author: Aaron Segura
License: License :: OSI Approved :: GNU General Public License v3 (GPLv3)
Project-URL: Homepage, https://github.com/aaronsegura/nextcloud-async
Project-URL: Bug Tracker, https://github.com/aaronsegura/nextcloud-async/issues
Keywords: nextcloud,asynchronous,spreed
Classifier: Development Status :: 3 - Alpha
Classifier: Framework :: Flake8
Classifier: Intended Audience :: Developers
Classifier: License :: OSI Approved :: GNU General Public License v3 (GPLv3)
Classifier: Natural Language :: English
Classifier: Programming Language :: Python :: 3.10
Requires-Python: >=3.10
License-File: LICENSE
Requires-Dist: httpx
Requires-Dist: xmltodict
Requires-Dist: platformdirs
Requires-Dist: PyNaCl
